meta/__init__.py
meta/api/__init__.py
meta/api/api.py
meta/api/api_request_sender.py
meta/api/consts.py
meta/api/message_sender.py
meta/api/messages/__init__.py
meta/api/messages/action_message.py
meta/api/messages/button_message.py
meta/api/messages/generic_message.py
meta/api/messages/media_message.py
meta/api/messages/message.py
meta/api/messages/quick_reply_message.py
meta/api/messages/text_message.py
metapython/__init__.py
metapython/api/__init__.py
metapython/api/api.py
metapython/api/api_request_sender.py
metapython/api/consts.py
metapython/api/message_sender.py
metapython/api/messages/__init__.py
metapython/api/messages/action_message.py
metapython/api/messages/button_message.py
metapython/api/messages/generic_message.py
metapython/api/messages/media_message.py
metapython/api/messages/message.py
metapython/api/messages/quick_reply_message.py
metapython/api/messages/text_message.py
tests/__init__.py
tests/api/__init__.py
tests/api/test_api_request_sender.py
tests/api/messages/__init__.py
tests/api/messages/test_action_message.py
tests/api/messages/test_button_message.py
tests/api/messages/test_generic_message.py
tests/api/messages/test_media_message.py
tests/api/messages/test_quick_reply_message.py
tests/api/messages/test_text_message.py
meta_api_python-0.1.0.dist-info/METADATA
meta_api_python-0.1.0.dist-info/WHEEL
meta_api_python-0.1.0.dist-info/top_level.txt
meta_api_python-0.1.0.dist-info/RECORD
