Metadata-Version: 2.1
Name: meta-api-python
Version: 0.1.0
Summary: Python wrapper to the various APIs in Meta Platform
Home-page: https://github.com/santoshdahal2016/meta-api-python.git
Author: Santosh Dahal
Author-email: dahalsantosh2018@gmail.com
License: UNKNOWN
Platform: UNKNOWN
Requires-Dist: requests
